gros_client/__init__.py
gros_client/mod.py
gros_client/robot.py
gros_client/robot_base.py
gros_client/robot_type.py
gros_client/robot/human.py
test_robot-1.0.0.dist-info/LICENSE
test_robot-1.0.0.dist-info/METADATA
test_robot-1.0.0.dist-info/WHEEL
test_robot-1.0.0.dist-info/top_level.txt
test_robot-1.0.0.dist-info/RECORD
